wat/__init__.py
wat/__main__.py
wat/wat.py
wat/pagesources/AbstractPage.py
wat/pagesources/BashHelpPage.py
wat/pagesources/CombinedPage.py
wat/pagesources/FSPathPage.py
wat/pagesources/FileCache.py
wat/pagesources/GlobTrie.py
wat/pagesources/NoPage.py
wat/pagesources/PackageManagerPage.py
wat/pagesources/SystemCtlPage.py
wat/pagesources/TLDRPage.py
wat/pagesources/WhatIsPage.py
wat/pagesources/__init__.py
wat_terminal-0.1.0.dist-info/LICENSE.md
wat_terminal-0.1.0.dist-info/METADATA
wat_terminal-0.1.0.dist-info/WHEEL
wat_terminal-0.1.0.dist-info/entry_points.txt
wat_terminal-0.1.0.dist-info/top_level.txt
wat_terminal-0.1.0.dist-info/RECORD
