Metadata-Version: 2.1
Name: wat-terminal
Version: 0.1.0
Summary: wat helps you find out what all the things in your Linux system are. You can ask it for information on: executables, services, bash built-ins, packages, files and folders
Home-page: https://github.com/codezeilen/wat
Author: Patrick Rein
Author-email: support@patrickrein.de
License: MIT License        
Platform: UNKNOWN
Classifier: Development Status :: 3 - Alpha
Classifier: Environment :: Console
Classifier: Intended Audience :: System Administrators
Classifier: Intended Audience :: Developers
Classifier: Topic :: System :: Shells
Classifier: License :: OSI Approved :: MIT License
Classifier: Programming Language :: Python :: 3.10
Classifier: Operating System :: POSIX :: Linux
Requires-Python: >=3.10
License-File: LICENSE.md
Requires-Dist: tldr (==3.1.0)
